ttaken.py
ttaken-0.4.1.dist-info/METADATA
ttaken-0.4.1.dist-info/WHEEL
ttaken-0.4.1.dist-info/top_level.txt
ttaken-0.4.1.dist-info/RECORD
