Metadata-Version: 2.1
Name: ttaken
Version: 0.4.1
Summary: Module to measure time taken by a given function
Home-page: https://github.com/sbusanelli/ttaken
Author: Sreedhar R Busanelli
Author-email: sbusanelli@gmail.com
Classifier: License :: OSI Approved :: MIT License
Classifier: Operating System :: OS Independent
